ext_auth/__init__.py
ext_auth/admin.py
ext_auth/apps.py
ext_auth/models.py
ext_auth/settings.py
ext_auth/tests.py
ext_auth/views.py
ext_auth/migrations/0001_initial.py
ext_auth/migrations/0002_auto_20210430_1858.py
ext_auth/migrations/0003_externaluseridentifier_app_id.py
ext_auth/migrations/__init__.py
ext_auth/rest_framework/__init__.py
ext_auth/rest_framework/exceptions.py
ext_auth/rest_framework/firebase.py
ext_auth/rest_framework/mixins.py
ext_auth/rest_framework/serializers.py
ext_auth-0.1.18.dist-info/LICENSE
ext_auth-0.1.18.dist-info/METADATA
ext_auth-0.1.18.dist-info/WHEEL
ext_auth-0.1.18.dist-info/top_level.txt
ext_auth-0.1.18.dist-info/RECORD
