Metadata-Version: 2.1
Name: ext-auth
Version: 0.1.18
Summary: A simple Django app register and login via 3rd party Auth
Home-page: https://github.com/cychongaspevo/ext-auth.git
Author: notfair
Author-email: cy.chong@aspevo.com
License: BSD License
Platform: UNKNOWN
Classifier: Environment :: Web Environment
Classifier: Framework :: Django
Classifier: Intended Audience :: Developers
Classifier: License :: OSI Approved :: BSD License
Classifier: Operating System :: OS Independent
Classifier: Programming Language :: Python
Classifier: Programming Language :: Python :: 2.7
Classifier: Programming Language :: Python :: 3
Classifier: Programming Language :: Python :: 3.2
Classifier: Programming Language :: Python :: 3.3
Classifier: Programming Language :: Python :: 3.4
Classifier: Programming Language :: Python :: 3.5
Classifier: Programming Language :: Python :: 3.6
Classifier: Topic :: Internet :: WWW/HTTP
Classifier: Topic :: Internet :: WWW/HTTP :: Dynamic Content
Requires-Dist: Django (>=1.7.7)
Requires-Dist: djangorestframework (>=3.1.1)
Requires-Dist: django-oauth-toolkit (>=0.10.0)
Requires-Dist: firebase-admin (>=2.10.0)
